README.rst
setup.py
array_collections/__init__.py
array_collections/_material_array.py
array_collections/_property_array.py
array_collections/_tuple_array.py
array_collections.egg-info/PKG-INFO
array_collections.egg-info/SOURCES.txt
array_collections.egg-info/dependency_links.txt
array_collections.egg-info/requires.txt
array_collections.egg-info/top_level.txt