Metadata-Version: 1.1
Name: array-collections
Version: 0.1.8
Summary: A collection of numpy ndarray subclasses.
Home-page: https://github.com/yoelcortes/array_collections
Author: Yoel Cortes-Pena
Author-email: yoelcortes@gmail.com
License: MIT
Download-URL: https://github.com/yoelcortes/array_collections.git
Platform: Windows
